setup.cfg
setup.py
astm_serial/__init__.py
astm_serial/client.py
astm_serial/codec.py
astm_serial/constanta.py
astm_serial.egg-info/PKG-INFO
astm_serial.egg-info/SOURCES.txt
astm_serial.egg-info/dependency_links.txt
astm_serial.egg-info/requires.txt
astm_serial.egg-info/top_level.txt
astm_serial.egg-info/zip-safe